stdin/__init__.py
stdin-2019.3.24.dist-info/METADATA
stdin-2019.3.24.dist-info/WHEEL
stdin-2019.3.24.dist-info/top_level.txt
stdin-2019.3.24.dist-info/RECORD
