Metadata-Version: 2.1
Name: stdin
Version: 2019.3.24
Summary: stdin.size(), stdin.read() functions
Home-page: https://github.com/looking-for-a-job/stdin.py
License: UNKNOWN
Keywords: stdin
Platform: UNKNOWN
Classifier: License :: Public Domain
Classifier: Operating System :: OS Independent
Classifier: Programming Language :: Python
Classifier: Programming Language :: Python :: 2
Classifier: Programming Language :: Python :: 2.7
Classifier: Programming Language :: Python :: 3
Classifier: Programming Language :: Python :: 3.4
Classifier: Programming Language :: Python :: 3.5
Classifier: Programming Language :: Python :: 3.6
Classifier: Programming Language :: Python :: 3.7
Classifier: Topic :: Software Development
Requires-Dist: public
Requires-Dist: setuptools
